feynman_learning/__init__.py
feynman_learning/ai_explainer.py
feynman_learning/cli.py
feynman_learning/config.py
feynman_learning/core.py
feynman_learning/session_manager.py
feynman_learning/tests/test_config.py
feynman_learning/tests/test_openai_compatible_provider.py
feynman_learning-0.1.0.dist-info/METADATA
feynman_learning-0.1.0.dist-info/WHEEL
feynman_learning-0.1.0.dist-info/entry_points.txt
feynman_learning-0.1.0.dist-info/top_level.txt
feynman_learning-0.1.0.dist-info/RECORD
