Metadata-Version: 2.4
Name: feynman-learning
Version: 0.1.0
Summary: AI-powered learning using the Feynman Technique with OpenAI and OpenAI-compatible models
Author-email: AI Learning Assistant <hemanth.hm@gmail.com>
License-Expression: MIT
Project-URL: Homepage, https://github.com/hemanth/feynman-learning
Project-URL: Repository, https://github.com/hemanth/feynman-learning
Project-URL: Issues, https://github.com/hemanth/feynman-learning/issues
Classifier: Development Status :: 3 - Alpha
Classifier: Intended Audience :: Education
Classifier: Operating System :: OS Independent
Classifier: Programming Language :: Python :: 3
Classifier: Programming Language :: Python :: 3.7
Classifier: Programming Language :: Python :: 3.8
Classifier: Programming Language :: Python :: 3.9
Classifier: Programming Language :: Python :: 3.10
Classifier: Programming Language :: Python :: 3.11
Classifier: Programming Language :: Python :: 3.12
Requires-Python: >=3.7
Requires-Dist: openai>=1.0.0
Provides-Extra: dev
Requires-Dist: pytest>=6.0; extra == "dev"
Requires-Dist: pytest-cov>=2.0; extra == "dev"
Requires-Dist: black>=21.0; extra == "dev"
Requires-Dist: flake8>=3.8; extra == "dev"
Requires-Dist: mypy>=0.910; extra == "dev"
